{
  "symbol_news": {
    "HPG": [
      {
        "id": "57f7d5fdccc77f75",
        "title": "C\u00e1ch Techcombank gi\u00fap ng\u01b0\u1eddi d\u00f9ng t\u1ed1i \u01b0u l\u1ee3i \u00edch t\u1eeb m\u1ecdi chi ti\u00eau h\u1eb1ng ng\u00e0y",
        "source": "VnExpress",
        "snippet": "Techcombank cho ph\u00e9p ng\u01b0\u1eddi d\u00f9ng t\u00edch l\u0169y U-Point t\u1eeb c\u00e1c giao d\u1ecbch h\u00e0ng ng\u00e0y va\u0300 du\u0300ng \u0111i\u00ea\u0309m th\u01b0\u01a1\u0309ng \u0111\u00ea\u0309 \u0111\u00f4\u0309i voucher ho\u0103\u0323c thanh toa\u0301n tr\u01b0\u0323c ti\u00ea\u0301p cho ca\u0301c giao di\u0323ch \u0103n u\u1ed1ng, mua s\u1eafm, di chuy\u1ec3n\u2026 \u0111\u00e1p ",
        "published_at": "2026-03-16T17:49:59.856084",
        "url": "https://vnexpress.net/cach-techcombank-giup-nguoi-dung-toi-uu-loi-ich-tu-moi-chi-tieu-hang-ngay-5044946.html",
        "scope": "market"
      },
      {
        "id": "85d43e6cd7b8ee29",
        "title": "GS25 Vi\u1ec7t Nam ghi d\u1ea5u \u1ea5n sau m\u1ed9t n\u0103m ho\u1ea1t \u0111\u1ed9ng t\u1ea1i H\u00e0 N\u1ed9i",
        "source": "VnExpress",
        "snippet": "GS25 gi\u1eef s\u1ee9c h\u00fat v\u1edbi ng\u01b0\u1eddi ti\u00eau d\u00f9ng tr\u1ebb, li\u00ean t\u1ee5c mang \u0111\u1ebfn tr\u1ea3i nghi\u1ec7m m\u1edbi cho th\u1ecb tr\u01b0\u1eddng b\u00e1n l\u1ebb ti\u1ec7n l\u1ee3i sau m\u1ed9t n\u0103m c\u00f3 m\u1eb7t t\u1ea1i th\u1ee7 \u0111\u00f4.",
        "published_at": "2026-03-16T17:49:59.856068",
        "url": "https://vnexpress.net/gs25-viet-nam-ghi-dau-an-sau-mot-nam-hoat-dong-tai-ha-noi-5050101.html",
        "scope": "market"
      },
      {
        "id": "ea284724da1430d8",
        "title": "Th\u00e9p c\u1ed1t b\u00ea t\u00f4ng Vi\u1ec7t Nam v\u00e0o M\u1ef9 ch\u1ecbu thu\u1ebf ch\u1ed1ng b\u00e1n ph\u00e1 gi\u00e1 \u0111\u1ebfn 130%",
        "source": "VnExpress",
        "snippet": "Th\u00e9p c\u1ed1t b\u00ea t\u00f4ng nh\u1eadp t\u1eeb Vi\u1ec7t Nam b\u1ecb \u00e1p thu\u1ebf ch\u1ed1ng b\u00e1n ph\u00e1 gi\u00e1 \u0111\u1ebfn 130%, theo k\u1ebft lu\u1eadn s\u01a1 b\u1ed9 c\u1ee7a B\u1ed9 Th\u01b0\u01a1ng m\u1ea1i M\u1ef9.",
        "published_at": "2026-03-16T17:49:59.856055",
        "url": "https://vnexpress.net/thep-cot-be-tong-viet-nam-vao-my-chiu-thue-chong-ban-pha-gia-den-130-5050224.html",
        "scope": "market"
      }
    ],
    "VNM": [
      {
        "id": "57f7d5fdccc77f75",
        "title": "C\u00e1ch Techcombank gi\u00fap ng\u01b0\u1eddi d\u00f9ng t\u1ed1i \u01b0u l\u1ee3i \u00edch t\u1eeb m\u1ecdi chi ti\u00eau h\u1eb1ng ng\u00e0y",
        "source": "VnExpress",
        "snippet": "Techcombank cho ph\u00e9p ng\u01b0\u1eddi d\u00f9ng t\u00edch l\u0169y U-Point t\u1eeb c\u00e1c giao d\u1ecbch h\u00e0ng ng\u00e0y va\u0300 du\u0300ng \u0111i\u00ea\u0309m th\u01b0\u01a1\u0309ng \u0111\u00ea\u0309 \u0111\u00f4\u0309i voucher ho\u0103\u0323c thanh toa\u0301n tr\u01b0\u0323c ti\u00ea\u0301p cho ca\u0301c giao di\u0323ch \u0103n u\u1ed1ng, mua s\u1eafm, di chuy\u1ec3n\u2026 \u0111\u00e1p ",
        "published_at": "2026-03-16T17:49:59.856084",
        "url": "https://vnexpress.net/cach-techcombank-giup-nguoi-dung-toi-uu-loi-ich-tu-moi-chi-tieu-hang-ngay-5044946.html",
        "scope": "market"
      },
      {
        "id": "85d43e6cd7b8ee29",
        "title": "GS25 Vi\u1ec7t Nam ghi d\u1ea5u \u1ea5n sau m\u1ed9t n\u0103m ho\u1ea1t \u0111\u1ed9ng t\u1ea1i H\u00e0 N\u1ed9i",
        "source": "VnExpress",
        "snippet": "GS25 gi\u1eef s\u1ee9c h\u00fat v\u1edbi ng\u01b0\u1eddi ti\u00eau d\u00f9ng tr\u1ebb, li\u00ean t\u1ee5c mang \u0111\u1ebfn tr\u1ea3i nghi\u1ec7m m\u1edbi cho th\u1ecb tr\u01b0\u1eddng b\u00e1n l\u1ebb ti\u1ec7n l\u1ee3i sau m\u1ed9t n\u0103m c\u00f3 m\u1eb7t t\u1ea1i th\u1ee7 \u0111\u00f4.",
        "published_at": "2026-03-16T17:49:59.856068",
        "url": "https://vnexpress.net/gs25-viet-nam-ghi-dau-an-sau-mot-nam-hoat-dong-tai-ha-noi-5050101.html",
        "scope": "market"
      },
      {
        "id": "ea284724da1430d8",
        "title": "Th\u00e9p c\u1ed1t b\u00ea t\u00f4ng Vi\u1ec7t Nam v\u00e0o M\u1ef9 ch\u1ecbu thu\u1ebf ch\u1ed1ng b\u00e1n ph\u00e1 gi\u00e1 \u0111\u1ebfn 130%",
        "source": "VnExpress",
        "snippet": "Th\u00e9p c\u1ed1t b\u00ea t\u00f4ng nh\u1eadp t\u1eeb Vi\u1ec7t Nam b\u1ecb \u00e1p thu\u1ebf ch\u1ed1ng b\u00e1n ph\u00e1 gi\u00e1 \u0111\u1ebfn 130%, theo k\u1ebft lu\u1eadn s\u01a1 b\u1ed9 c\u1ee7a B\u1ed9 Th\u01b0\u01a1ng m\u1ea1i M\u1ef9.",
        "published_at": "2026-03-16T17:49:59.856055",
        "url": "https://vnexpress.net/thep-cot-be-tong-viet-nam-vao-my-chiu-thue-chong-ban-pha-gia-den-130-5050224.html",
        "scope": "market"
      }
    ],
    "FPT": [
      {
        "id": "57f7d5fdccc77f75",
        "title": "C\u00e1ch Techcombank gi\u00fap ng\u01b0\u1eddi d\u00f9ng t\u1ed1i \u01b0u l\u1ee3i \u00edch t\u1eeb m\u1ecdi chi ti\u00eau h\u1eb1ng ng\u00e0y",
        "source": "VnExpress",
        "snippet": "Techcombank cho ph\u00e9p ng\u01b0\u1eddi d\u00f9ng t\u00edch l\u0169y U-Point t\u1eeb c\u00e1c giao d\u1ecbch h\u00e0ng ng\u00e0y va\u0300 du\u0300ng \u0111i\u00ea\u0309m th\u01b0\u01a1\u0309ng \u0111\u00ea\u0309 \u0111\u00f4\u0309i voucher ho\u0103\u0323c thanh toa\u0301n tr\u01b0\u0323c ti\u00ea\u0301p cho ca\u0301c giao di\u0323ch \u0103n u\u1ed1ng, mua s\u1eafm, di chuy\u1ec3n\u2026 \u0111\u00e1p ",
        "published_at": "2026-03-16T17:49:59.856084",
        "url": "https://vnexpress.net/cach-techcombank-giup-nguoi-dung-toi-uu-loi-ich-tu-moi-chi-tieu-hang-ngay-5044946.html",
        "scope": "market"
      },
      {
        "id": "85d43e6cd7b8ee29",
        "title": "GS25 Vi\u1ec7t Nam ghi d\u1ea5u \u1ea5n sau m\u1ed9t n\u0103m ho\u1ea1t \u0111\u1ed9ng t\u1ea1i H\u00e0 N\u1ed9i",
        "source": "VnExpress",
        "snippet": "GS25 gi\u1eef s\u1ee9c h\u00fat v\u1edbi ng\u01b0\u1eddi ti\u00eau d\u00f9ng tr\u1ebb, li\u00ean t\u1ee5c mang \u0111\u1ebfn tr\u1ea3i nghi\u1ec7m m\u1edbi cho th\u1ecb tr\u01b0\u1eddng b\u00e1n l\u1ebb ti\u1ec7n l\u1ee3i sau m\u1ed9t n\u0103m c\u00f3 m\u1eb7t t\u1ea1i th\u1ee7 \u0111\u00f4.",
        "published_at": "2026-03-16T17:49:59.856068",
        "url": "https://vnexpress.net/gs25-viet-nam-ghi-dau-an-sau-mot-nam-hoat-dong-tai-ha-noi-5050101.html",
        "scope": "market"
      },
      {
        "id": "ea284724da1430d8",
        "title": "Th\u00e9p c\u1ed1t b\u00ea t\u00f4ng Vi\u1ec7t Nam v\u00e0o M\u1ef9 ch\u1ecbu thu\u1ebf ch\u1ed1ng b\u00e1n ph\u00e1 gi\u00e1 \u0111\u1ebfn 130%",
        "source": "VnExpress",
        "snippet": "Th\u00e9p c\u1ed1t b\u00ea t\u00f4ng nh\u1eadp t\u1eeb Vi\u1ec7t Nam b\u1ecb \u00e1p thu\u1ebf ch\u1ed1ng b\u00e1n ph\u00e1 gi\u00e1 \u0111\u1ebfn 130%, theo k\u1ebft lu\u1eadn s\u01a1 b\u1ed9 c\u1ee7a B\u1ed9 Th\u01b0\u01a1ng m\u1ea1i M\u1ef9.",
        "published_at": "2026-03-16T17:49:59.856055",
        "url": "https://vnexpress.net/thep-cot-be-tong-viet-nam-vao-my-chiu-thue-chong-ban-pha-gia-den-130-5050224.html",
        "scope": "market"
      }
    ],
    "MWG": [
      {
        "id": "57f7d5fdccc77f75",
        "title": "C\u00e1ch Techcombank gi\u00fap ng\u01b0\u1eddi d\u00f9ng t\u1ed1i \u01b0u l\u1ee3i \u00edch t\u1eeb m\u1ecdi chi ti\u00eau h\u1eb1ng ng\u00e0y",
        "source": "VnExpress",
        "snippet": "Techcombank cho ph\u00e9p ng\u01b0\u1eddi d\u00f9ng t\u00edch l\u0169y U-Point t\u1eeb c\u00e1c giao d\u1ecbch h\u00e0ng ng\u00e0y va\u0300 du\u0300ng \u0111i\u00ea\u0309m th\u01b0\u01a1\u0309ng \u0111\u00ea\u0309 \u0111\u00f4\u0309i voucher ho\u0103\u0323c thanh toa\u0301n tr\u01b0\u0323c ti\u00ea\u0301p cho ca\u0301c giao di\u0323ch \u0103n u\u1ed1ng, mua s\u1eafm, di chuy\u1ec3n\u2026 \u0111\u00e1p ",
        "published_at": "2026-03-16T17:49:59.856084",
        "url": "https://vnexpress.net/cach-techcombank-giup-nguoi-dung-toi-uu-loi-ich-tu-moi-chi-tieu-hang-ngay-5044946.html",
        "scope": "market"
      },
      {
        "id": "85d43e6cd7b8ee29",
        "title": "GS25 Vi\u1ec7t Nam ghi d\u1ea5u \u1ea5n sau m\u1ed9t n\u0103m ho\u1ea1t \u0111\u1ed9ng t\u1ea1i H\u00e0 N\u1ed9i",
        "source": "VnExpress",
        "snippet": "GS25 gi\u1eef s\u1ee9c h\u00fat v\u1edbi ng\u01b0\u1eddi ti\u00eau d\u00f9ng tr\u1ebb, li\u00ean t\u1ee5c mang \u0111\u1ebfn tr\u1ea3i nghi\u1ec7m m\u1edbi cho th\u1ecb tr\u01b0\u1eddng b\u00e1n l\u1ebb ti\u1ec7n l\u1ee3i sau m\u1ed9t n\u0103m c\u00f3 m\u1eb7t t\u1ea1i th\u1ee7 \u0111\u00f4.",
        "published_at": "2026-03-16T17:49:59.856068",
        "url": "https://vnexpress.net/gs25-viet-nam-ghi-dau-an-sau-mot-nam-hoat-dong-tai-ha-noi-5050101.html",
        "scope": "market"
      },
      {
        "id": "ea284724da1430d8",
        "title": "Th\u00e9p c\u1ed1t b\u00ea t\u00f4ng Vi\u1ec7t Nam v\u00e0o M\u1ef9 ch\u1ecbu thu\u1ebf ch\u1ed1ng b\u00e1n ph\u00e1 gi\u00e1 \u0111\u1ebfn 130%",
        "source": "VnExpress",
        "snippet": "Th\u00e9p c\u1ed1t b\u00ea t\u00f4ng nh\u1eadp t\u1eeb Vi\u1ec7t Nam b\u1ecb \u00e1p thu\u1ebf ch\u1ed1ng b\u00e1n ph\u00e1 gi\u00e1 \u0111\u1ebfn 130%, theo k\u1ebft lu\u1eadn s\u01a1 b\u1ed9 c\u1ee7a B\u1ed9 Th\u01b0\u01a1ng m\u1ea1i M\u1ef9.",
        "published_at": "2026-03-16T17:49:59.856055",
        "url": "https://vnexpress.net/thep-cot-be-tong-viet-nam-vao-my-chiu-thue-chong-ban-pha-gia-den-130-5050224.html",
        "scope": "market"
      }
    ],
    "VCB": [
      {
        "id": "57f7d5fdccc77f75",
        "title": "C\u00e1ch Techcombank gi\u00fap ng\u01b0\u1eddi d\u00f9ng t\u1ed1i \u01b0u l\u1ee3i \u00edch t\u1eeb m\u1ecdi chi ti\u00eau h\u1eb1ng ng\u00e0y",
        "source": "VnExpress",
        "snippet": "Techcombank cho ph\u00e9p ng\u01b0\u1eddi d\u00f9ng t\u00edch l\u0169y U-Point t\u1eeb c\u00e1c giao d\u1ecbch h\u00e0ng ng\u00e0y va\u0300 du\u0300ng \u0111i\u00ea\u0309m th\u01b0\u01a1\u0309ng \u0111\u00ea\u0309 \u0111\u00f4\u0309i voucher ho\u0103\u0323c thanh toa\u0301n tr\u01b0\u0323c ti\u00ea\u0301p cho ca\u0301c giao di\u0323ch \u0103n u\u1ed1ng, mua s\u1eafm, di chuy\u1ec3n\u2026 \u0111\u00e1p ",
        "published_at": "2026-03-16T17:49:59.856084",
        "url": "https://vnexpress.net/cach-techcombank-giup-nguoi-dung-toi-uu-loi-ich-tu-moi-chi-tieu-hang-ngay-5044946.html",
        "scope": "market"
      },
      {
        "id": "85d43e6cd7b8ee29",
        "title": "GS25 Vi\u1ec7t Nam ghi d\u1ea5u \u1ea5n sau m\u1ed9t n\u0103m ho\u1ea1t \u0111\u1ed9ng t\u1ea1i H\u00e0 N\u1ed9i",
        "source": "VnExpress",
        "snippet": "GS25 gi\u1eef s\u1ee9c h\u00fat v\u1edbi ng\u01b0\u1eddi ti\u00eau d\u00f9ng tr\u1ebb, li\u00ean t\u1ee5c mang \u0111\u1ebfn tr\u1ea3i nghi\u1ec7m m\u1edbi cho th\u1ecb tr\u01b0\u1eddng b\u00e1n l\u1ebb ti\u1ec7n l\u1ee3i sau m\u1ed9t n\u0103m c\u00f3 m\u1eb7t t\u1ea1i th\u1ee7 \u0111\u00f4.",
        "published_at": "2026-03-16T17:49:59.856068",
        "url": "https://vnexpress.net/gs25-viet-nam-ghi-dau-an-sau-mot-nam-hoat-dong-tai-ha-noi-5050101.html",
        "scope": "market"
      },
      {
        "id": "ea284724da1430d8",
        "title": "Th\u00e9p c\u1ed1t b\u00ea t\u00f4ng Vi\u1ec7t Nam v\u00e0o M\u1ef9 ch\u1ecbu thu\u1ebf ch\u1ed1ng b\u00e1n ph\u00e1 gi\u00e1 \u0111\u1ebfn 130%",
        "source": "VnExpress",
        "snippet": "Th\u00e9p c\u1ed1t b\u00ea t\u00f4ng nh\u1eadp t\u1eeb Vi\u1ec7t Nam b\u1ecb \u00e1p thu\u1ebf ch\u1ed1ng b\u00e1n ph\u00e1 gi\u00e1 \u0111\u1ebfn 130%, theo k\u1ebft lu\u1eadn s\u01a1 b\u1ed9 c\u1ee7a B\u1ed9 Th\u01b0\u01a1ng m\u1ea1i M\u1ef9.",
        "published_at": "2026-03-16T17:49:59.856055",
        "url": "https://vnexpress.net/thep-cot-be-tong-viet-nam-vao-my-chiu-thue-chong-ban-pha-gia-den-130-5050224.html",
        "scope": "market"
      }
    ],
    "TCB": [
      {
        "id": "57f7d5fdccc77f75",
        "title": "C\u00e1ch Techcombank gi\u00fap ng\u01b0\u1eddi d\u00f9ng t\u1ed1i \u01b0u l\u1ee3i \u00edch t\u1eeb m\u1ecdi chi ti\u00eau h\u1eb1ng ng\u00e0y",
        "source": "VnExpress",
        "snippet": "Techcombank cho ph\u00e9p ng\u01b0\u1eddi d\u00f9ng t\u00edch l\u0169y U-Point t\u1eeb c\u00e1c giao d\u1ecbch h\u00e0ng ng\u00e0y va\u0300 du\u0300ng \u0111i\u00ea\u0309m th\u01b0\u01a1\u0309ng \u0111\u00ea\u0309 \u0111\u00f4\u0309i voucher ho\u0103\u0323c thanh toa\u0301n tr\u01b0\u0323c ti\u00ea\u0301p cho ca\u0301c giao di\u0323ch \u0103n u\u1ed1ng, mua s\u1eafm, di chuy\u1ec3n\u2026 \u0111\u00e1p ",
        "published_at": "2026-03-16T17:49:59.856084",
        "url": "https://vnexpress.net/cach-techcombank-giup-nguoi-dung-toi-uu-loi-ich-tu-moi-chi-tieu-hang-ngay-5044946.html",
        "scope": "symbol"
      },
      {
        "id": "85d43e6cd7b8ee29",
        "title": "GS25 Vi\u1ec7t Nam ghi d\u1ea5u \u1ea5n sau m\u1ed9t n\u0103m ho\u1ea1t \u0111\u1ed9ng t\u1ea1i H\u00e0 N\u1ed9i",
        "source": "VnExpress",
        "snippet": "GS25 gi\u1eef s\u1ee9c h\u00fat v\u1edbi ng\u01b0\u1eddi ti\u00eau d\u00f9ng tr\u1ebb, li\u00ean t\u1ee5c mang \u0111\u1ebfn tr\u1ea3i nghi\u1ec7m m\u1edbi cho th\u1ecb tr\u01b0\u1eddng b\u00e1n l\u1ebb ti\u1ec7n l\u1ee3i sau m\u1ed9t n\u0103m c\u00f3 m\u1eb7t t\u1ea1i th\u1ee7 \u0111\u00f4.",
        "published_at": "2026-03-16T17:49:59.856068",
        "url": "https://vnexpress.net/gs25-viet-nam-ghi-dau-an-sau-mot-nam-hoat-dong-tai-ha-noi-5050101.html",
        "scope": "market"
      },
      {
        "id": "ea284724da1430d8",
        "title": "Th\u00e9p c\u1ed1t b\u00ea t\u00f4ng Vi\u1ec7t Nam v\u00e0o M\u1ef9 ch\u1ecbu thu\u1ebf ch\u1ed1ng b\u00e1n ph\u00e1 gi\u00e1 \u0111\u1ebfn 130%",
        "source": "VnExpress",
        "snippet": "Th\u00e9p c\u1ed1t b\u00ea t\u00f4ng nh\u1eadp t\u1eeb Vi\u1ec7t Nam b\u1ecb \u00e1p thu\u1ebf ch\u1ed1ng b\u00e1n ph\u00e1 gi\u00e1 \u0111\u1ebfn 130%, theo k\u1ebft lu\u1eadn s\u01a1 b\u1ed9 c\u1ee7a B\u1ed9 Th\u01b0\u01a1ng m\u1ea1i M\u1ef9.",
        "published_at": "2026-03-16T17:49:59.856055",
        "url": "https://vnexpress.net/thep-cot-be-tong-viet-nam-vao-my-chiu-thue-chong-ban-pha-gia-den-130-5050224.html",
        "scope": "market"
      },
      {
        "id": "9c8f162297ce068f",
        "title": "N\u00f4ng d\u00e2n M\u1ef9 \u1ed3 \u1ea1t m\u1edf b\u00e1n ng\u00f4, \u0111\u1eadu t\u01b0\u01a1ng",
        "source": "VnExpress",
        "snippet": "T\u1eadn d\u1ee5ng gi\u00e1 ng\u0169 c\u1ed1c t\u0103ng m\u1ea1nh k\u1ec3 t\u1eeb xung \u0111\u1ed9t Trung \u0110\u00f4ng, n\u00f4ng d\u00e2n \u1ed3 \u1ea1t b\u00e1n ng\u00f4 v\u00e0 \u0111\u1eadu t\u01b0\u01a1ng \u0111\u00e3 tr\u1eef l\u1ea1i t\u1eeb v\u1ee5 m\u00f9a n\u0103m ngo\u00e1i.",
        "published_at": "2026-03-16T17:49:59.856042",
        "url": "https://vnexpress.net/nong-dan-my-o-at-mo-ban-ngo-dau-tuong-5050214.html",
        "scope": "market"
      }
    ],
    "MBB": [
      {
        "id": "57f7d5fdccc77f75",
        "title": "C\u00e1ch Techcombank gi\u00fap ng\u01b0\u1eddi d\u00f9ng t\u1ed1i \u01b0u l\u1ee3i \u00edch t\u1eeb m\u1ecdi chi ti\u00eau h\u1eb1ng ng\u00e0y",
        "source": "VnExpress",
        "snippet": "Techcombank cho ph\u00e9p ng\u01b0\u1eddi d\u00f9ng t\u00edch l\u0169y U-Point t\u1eeb c\u00e1c giao d\u1ecbch h\u00e0ng ng\u00e0y va\u0300 du\u0300ng \u0111i\u00ea\u0309m th\u01b0\u01a1\u0309ng \u0111\u00ea\u0309 \u0111\u00f4\u0309i voucher ho\u0103\u0323c thanh toa\u0301n tr\u01b0\u0323c ti\u00ea\u0301p cho ca\u0301c giao di\u0323ch \u0103n u\u1ed1ng, mua s\u1eafm, di chuy\u1ec3n\u2026 \u0111\u00e1p ",
        "published_at": "2026-03-16T17:49:59.856084",
        "url": "https://vnexpress.net/cach-techcombank-giup-nguoi-dung-toi-uu-loi-ich-tu-moi-chi-tieu-hang-ngay-5044946.html",
        "scope": "market"
      },
      {
        "id": "85d43e6cd7b8ee29",
        "title": "GS25 Vi\u1ec7t Nam ghi d\u1ea5u \u1ea5n sau m\u1ed9t n\u0103m ho\u1ea1t \u0111\u1ed9ng t\u1ea1i H\u00e0 N\u1ed9i",
        "source": "VnExpress",
        "snippet": "GS25 gi\u1eef s\u1ee9c h\u00fat v\u1edbi ng\u01b0\u1eddi ti\u00eau d\u00f9ng tr\u1ebb, li\u00ean t\u1ee5c mang \u0111\u1ebfn tr\u1ea3i nghi\u1ec7m m\u1edbi cho th\u1ecb tr\u01b0\u1eddng b\u00e1n l\u1ebb ti\u1ec7n l\u1ee3i sau m\u1ed9t n\u0103m c\u00f3 m\u1eb7t t\u1ea1i th\u1ee7 \u0111\u00f4.",
        "published_at": "2026-03-16T17:49:59.856068",
        "url": "https://vnexpress.net/gs25-viet-nam-ghi-dau-an-sau-mot-nam-hoat-dong-tai-ha-noi-5050101.html",
        "scope": "market"
      },
      {
        "id": "ea284724da1430d8",
        "title": "Th\u00e9p c\u1ed1t b\u00ea t\u00f4ng Vi\u1ec7t Nam v\u00e0o M\u1ef9 ch\u1ecbu thu\u1ebf ch\u1ed1ng b\u00e1n ph\u00e1 gi\u00e1 \u0111\u1ebfn 130%",
        "source": "VnExpress",
        "snippet": "Th\u00e9p c\u1ed1t b\u00ea t\u00f4ng nh\u1eadp t\u1eeb Vi\u1ec7t Nam b\u1ecb \u00e1p thu\u1ebf ch\u1ed1ng b\u00e1n ph\u00e1 gi\u00e1 \u0111\u1ebfn 130%, theo k\u1ebft lu\u1eadn s\u01a1 b\u1ed9 c\u1ee7a B\u1ed9 Th\u01b0\u01a1ng m\u1ea1i M\u1ef9.",
        "published_at": "2026-03-16T17:49:59.856055",
        "url": "https://vnexpress.net/thep-cot-be-tong-viet-nam-vao-my-chiu-thue-chong-ban-pha-gia-den-130-5050224.html",
        "scope": "market"
      }
    ],
    "ACB": [
      {
        "id": "57f7d5fdccc77f75",
        "title": "C\u00e1ch Techcombank gi\u00fap ng\u01b0\u1eddi d\u00f9ng t\u1ed1i \u01b0u l\u1ee3i \u00edch t\u1eeb m\u1ecdi chi ti\u00eau h\u1eb1ng ng\u00e0y",
        "source": "VnExpress",
        "snippet": "Techcombank cho ph\u00e9p ng\u01b0\u1eddi d\u00f9ng t\u00edch l\u0169y U-Point t\u1eeb c\u00e1c giao d\u1ecbch h\u00e0ng ng\u00e0y va\u0300 du\u0300ng \u0111i\u00ea\u0309m th\u01b0\u01a1\u0309ng \u0111\u00ea\u0309 \u0111\u00f4\u0309i voucher ho\u0103\u0323c thanh toa\u0301n tr\u01b0\u0323c ti\u00ea\u0301p cho ca\u0301c giao di\u0323ch \u0103n u\u1ed1ng, mua s\u1eafm, di chuy\u1ec3n\u2026 \u0111\u00e1p ",
        "published_at": "2026-03-16T17:49:59.856084",
        "url": "https://vnexpress.net/cach-techcombank-giup-nguoi-dung-toi-uu-loi-ich-tu-moi-chi-tieu-hang-ngay-5044946.html",
        "scope": "market"
      },
      {
        "id": "85d43e6cd7b8ee29",
        "title": "GS25 Vi\u1ec7t Nam ghi d\u1ea5u \u1ea5n sau m\u1ed9t n\u0103m ho\u1ea1t \u0111\u1ed9ng t\u1ea1i H\u00e0 N\u1ed9i",
        "source": "VnExpress",
        "snippet": "GS25 gi\u1eef s\u1ee9c h\u00fat v\u1edbi ng\u01b0\u1eddi ti\u00eau d\u00f9ng tr\u1ebb, li\u00ean t\u1ee5c mang \u0111\u1ebfn tr\u1ea3i nghi\u1ec7m m\u1edbi cho th\u1ecb tr\u01b0\u1eddng b\u00e1n l\u1ebb ti\u1ec7n l\u1ee3i sau m\u1ed9t n\u0103m c\u00f3 m\u1eb7t t\u1ea1i th\u1ee7 \u0111\u00f4.",
        "published_at": "2026-03-16T17:49:59.856068",
        "url": "https://vnexpress.net/gs25-viet-nam-ghi-dau-an-sau-mot-nam-hoat-dong-tai-ha-noi-5050101.html",
        "scope": "market"
      },
      {
        "id": "ea284724da1430d8",
        "title": "Th\u00e9p c\u1ed1t b\u00ea t\u00f4ng Vi\u1ec7t Nam v\u00e0o M\u1ef9 ch\u1ecbu thu\u1ebf ch\u1ed1ng b\u00e1n ph\u00e1 gi\u00e1 \u0111\u1ebfn 130%",
        "source": "VnExpress",
        "snippet": "Th\u00e9p c\u1ed1t b\u00ea t\u00f4ng nh\u1eadp t\u1eeb Vi\u1ec7t Nam b\u1ecb \u00e1p thu\u1ebf ch\u1ed1ng b\u00e1n ph\u00e1 gi\u00e1 \u0111\u1ebfn 130%, theo k\u1ebft lu\u1eadn s\u01a1 b\u1ed9 c\u1ee7a B\u1ed9 Th\u01b0\u01a1ng m\u1ea1i M\u1ef9.",
        "published_at": "2026-03-16T17:49:59.856055",
        "url": "https://vnexpress.net/thep-cot-be-tong-viet-nam-vao-my-chiu-thue-chong-ban-pha-gia-den-130-5050224.html",
        "scope": "market"
      }
    ],
    "BID": [
      {
        "id": "57f7d5fdccc77f75",
        "title": "C\u00e1ch Techcombank gi\u00fap ng\u01b0\u1eddi d\u00f9ng t\u1ed1i \u01b0u l\u1ee3i \u00edch t\u1eeb m\u1ecdi chi ti\u00eau h\u1eb1ng ng\u00e0y",
        "source": "VnExpress",
        "snippet": "Techcombank cho ph\u00e9p ng\u01b0\u1eddi d\u00f9ng t\u00edch l\u0169y U-Point t\u1eeb c\u00e1c giao d\u1ecbch h\u00e0ng ng\u00e0y va\u0300 du\u0300ng \u0111i\u00ea\u0309m th\u01b0\u01a1\u0309ng \u0111\u00ea\u0309 \u0111\u00f4\u0309i voucher ho\u0103\u0323c thanh toa\u0301n tr\u01b0\u0323c ti\u00ea\u0301p cho ca\u0301c giao di\u0323ch \u0103n u\u1ed1ng, mua s\u1eafm, di chuy\u1ec3n\u2026 \u0111\u00e1p ",
        "published_at": "2026-03-16T17:49:59.856084",
        "url": "https://vnexpress.net/cach-techcombank-giup-nguoi-dung-toi-uu-loi-ich-tu-moi-chi-tieu-hang-ngay-5044946.html",
        "scope": "market"
      },
      {
        "id": "85d43e6cd7b8ee29",
        "title": "GS25 Vi\u1ec7t Nam ghi d\u1ea5u \u1ea5n sau m\u1ed9t n\u0103m ho\u1ea1t \u0111\u1ed9ng t\u1ea1i H\u00e0 N\u1ed9i",
        "source": "VnExpress",
        "snippet": "GS25 gi\u1eef s\u1ee9c h\u00fat v\u1edbi ng\u01b0\u1eddi ti\u00eau d\u00f9ng tr\u1ebb, li\u00ean t\u1ee5c mang \u0111\u1ebfn tr\u1ea3i nghi\u1ec7m m\u1edbi cho th\u1ecb tr\u01b0\u1eddng b\u00e1n l\u1ebb ti\u1ec7n l\u1ee3i sau m\u1ed9t n\u0103m c\u00f3 m\u1eb7t t\u1ea1i th\u1ee7 \u0111\u00f4.",
        "published_at": "2026-03-16T17:49:59.856068",
        "url": "https://vnexpress.net/gs25-viet-nam-ghi-dau-an-sau-mot-nam-hoat-dong-tai-ha-noi-5050101.html",
        "scope": "market"
      },
      {
        "id": "ea284724da1430d8",
        "title": "Th\u00e9p c\u1ed1t b\u00ea t\u00f4ng Vi\u1ec7t Nam v\u00e0o M\u1ef9 ch\u1ecbu thu\u1ebf ch\u1ed1ng b\u00e1n ph\u00e1 gi\u00e1 \u0111\u1ebfn 130%",
        "source": "VnExpress",
        "snippet": "Th\u00e9p c\u1ed1t b\u00ea t\u00f4ng nh\u1eadp t\u1eeb Vi\u1ec7t Nam b\u1ecb \u00e1p thu\u1ebf ch\u1ed1ng b\u00e1n ph\u00e1 gi\u00e1 \u0111\u1ebfn 130%, theo k\u1ebft lu\u1eadn s\u01a1 b\u1ed9 c\u1ee7a B\u1ed9 Th\u01b0\u01a1ng m\u1ea1i M\u1ef9.",
        "published_at": "2026-03-16T17:49:59.856055",
        "url": "https://vnexpress.net/thep-cot-be-tong-viet-nam-vao-my-chiu-thue-chong-ban-pha-gia-den-130-5050224.html",
        "scope": "market"
      }
    ],
    "CTG": [
      {
        "id": "90c6cff3c6cbc8ef",
        "title": "Ti\u1ebfp t\u1ee5c x\u1ea3 qu\u1ef9 b\u00ecnh \u1ed5n gi\u1eef gi\u00e1 x\u0103ng d\u1ea7u",
        "source": "VnExpress",
        "snippet": "\u0110\u1ec3 gi\u1eef gi\u00e1 x\u0103ng kh\u00f4ng t\u0103ng, li\u00ean B\u1ed9 C\u00f4ng Th\u01b0\u01a1ng - T\u00e0i ch\u00ednh ti\u1ebfp t\u1ee5c chi 4.000 \u0111\u1ed3ng m\u1ed7i l\u00edt t\u1eeb Qu\u1ef9 b\u00ecnh \u1ed5n \u1edf k\u1ef3 \u0111i\u1ec1u h\u00e0nh h\u00f4m nay.",
        "published_at": "2026-03-16T17:49:59.855930",
        "url": "https://vnexpress.net/gia-xang-dau-moi-nhat-hom-nay-14-3-5050498.html",
        "scope": "symbol"
      },
      {
        "id": "57f7d5fdccc77f75",
        "title": "C\u00e1ch Techcombank gi\u00fap ng\u01b0\u1eddi d\u00f9ng t\u1ed1i \u01b0u l\u1ee3i \u00edch t\u1eeb m\u1ecdi chi ti\u00eau h\u1eb1ng ng\u00e0y",
        "source": "VnExpress",
        "snippet": "Techcombank cho ph\u00e9p ng\u01b0\u1eddi d\u00f9ng t\u00edch l\u0169y U-Point t\u1eeb c\u00e1c giao d\u1ecbch h\u00e0ng ng\u00e0y va\u0300 du\u0300ng \u0111i\u00ea\u0309m th\u01b0\u01a1\u0309ng \u0111\u00ea\u0309 \u0111\u00f4\u0309i voucher ho\u0103\u0323c thanh toa\u0301n tr\u01b0\u0323c ti\u00ea\u0301p cho ca\u0301c giao di\u0323ch \u0103n u\u1ed1ng, mua s\u1eafm, di chuy\u1ec3n\u2026 \u0111\u00e1p ",
        "published_at": "2026-03-16T17:49:59.856084",
        "url": "https://vnexpress.net/cach-techcombank-giup-nguoi-dung-toi-uu-loi-ich-tu-moi-chi-tieu-hang-ngay-5044946.html",
        "scope": "market"
      },
      {
        "id": "85d43e6cd7b8ee29",
        "title": "GS25 Vi\u1ec7t Nam ghi d\u1ea5u \u1ea5n sau m\u1ed9t n\u0103m ho\u1ea1t \u0111\u1ed9ng t\u1ea1i H\u00e0 N\u1ed9i",
        "source": "VnExpress",
        "snippet": "GS25 gi\u1eef s\u1ee9c h\u00fat v\u1edbi ng\u01b0\u1eddi ti\u00eau d\u00f9ng tr\u1ebb, li\u00ean t\u1ee5c mang \u0111\u1ebfn tr\u1ea3i nghi\u1ec7m m\u1edbi cho th\u1ecb tr\u01b0\u1eddng b\u00e1n l\u1ebb ti\u1ec7n l\u1ee3i sau m\u1ed9t n\u0103m c\u00f3 m\u1eb7t t\u1ea1i th\u1ee7 \u0111\u00f4.",
        "published_at": "2026-03-16T17:49:59.856068",
        "url": "https://vnexpress.net/gs25-viet-nam-ghi-dau-an-sau-mot-nam-hoat-dong-tai-ha-noi-5050101.html",
        "scope": "market"
      },
      {
        "id": "ea284724da1430d8",
        "title": "Th\u00e9p c\u1ed1t b\u00ea t\u00f4ng Vi\u1ec7t Nam v\u00e0o M\u1ef9 ch\u1ecbu thu\u1ebf ch\u1ed1ng b\u00e1n ph\u00e1 gi\u00e1 \u0111\u1ebfn 130%",
        "source": "VnExpress",
        "snippet": "Th\u00e9p c\u1ed1t b\u00ea t\u00f4ng nh\u1eadp t\u1eeb Vi\u1ec7t Nam b\u1ecb \u00e1p thu\u1ebf ch\u1ed1ng b\u00e1n ph\u00e1 gi\u00e1 \u0111\u1ebfn 130%, theo k\u1ebft lu\u1eadn s\u01a1 b\u1ed9 c\u1ee7a B\u1ed9 Th\u01b0\u01a1ng m\u1ea1i M\u1ef9.",
        "published_at": "2026-03-16T17:49:59.856055",
        "url": "https://vnexpress.net/thep-cot-be-tong-viet-nam-vao-my-chiu-thue-chong-ban-pha-gia-den-130-5050224.html",
        "scope": "market"
      }
    ]
  },
  "fetched_at": "2026-03-16T17:49:59.993782",
  "symbols": [
    "HPG",
    "VNM",
    "FPT",
    "MWG",
    "VCB",
    "TCB",
    "MBB",
    "ACB",
    "BID",
    "CTG"
  ],
  "days_back": 7,
  "MWG_e0f84cdbd4bf": {
    "symbol_scores": [
      {
        "symbol": "MWG",
        "buy_potential_score": 70,
        "risk_score": 30,
        "confidence": 0.6,
        "horizon": "1-4w",
        "key_bull_points": [
          "GS25 Vietnam reports strong performance after one year of operation in Hanoi, indicating growth potential for the retail industry in Vietnam"
        ],
        "key_risks": [
          "Vietnam's steel prices have increased by 130%, potentially affecting the construction industry and having a negative impact on MWG"
        ],
        "evidence": [
          {
            "id": "news1",
            "supports": "bull_point"
          },
          {
            "id": "news2",
            "supports": "risk"
          },
          {
            "id": "news3",
            "supports": "bull_point"
          }
        ]
      }
    ]
  }
}