{
  "generated_at": "2026-03-05T07:11:15.957014",
  "strategy_id": "trend_momentum_atr_regime_adaptive",
  "strategy_version": "1.0.0",
  "allocation_targets": {
    "stock": 0.6,
    "bond_fund": 0.4
  },
  "recommendations": [
    {
      "symbol": "STB",
      "asset_class": "stock",
      "action": "BUY",
      "buy_zone_low": 60.0,
      "buy_zone_high": 60.0,
      "stop_loss": 50.0,
      "take_profit": 80.0,
      "position_target_pct": 0.09,
      "rationale_bullets": [
        "Regime: BULL | RSI\u226550",
        "Trend UP: price 66 > MA10w 61 > MA30w 56",
        "RSI(14): 67.5",
        "ATR: 5",
        "Vol: 57,433,800 (1.0x avg)",
        "Entry: pullback mid-zone",
        "Position: 9.0% (base 6.0% \u00d7 1.5x = 9.0%, stop dist 16.7%)"
      ],
      "entry_type": "pullback",
      "breakout_level": 0.0,
      "entry_price": 60.0,
      "signal_week_end": "2026-03-05",
      "earliest_entry_date": null
    },
    {
      "symbol": "VIC",
      "asset_class": "stock",
      "action": "BUY",
      "buy_zone_low": 140.0,
      "buy_zone_high": 150.0,
      "stop_loss": 110.0,
      "take_profit": 230.0,
      "position_target_pct": 0.0562,
      "rationale_bullets": [
        "Regime: BULL | RSI\u226550",
        "Trend UP: price 163 > MA10w 159 > MA30w 117",
        "RSI(14): 64.4",
        "ATR: 23",
        "Vol: 20,854,100 (0.7x avg)",
        "Entry: pullback mid-zone",
        "Position: 5.6% (base 3.8% \u00d7 1.5x = 5.6%, stop dist 26.7%)"
      ],
      "entry_type": "pullback",
      "breakout_level": 0.0,
      "entry_price": 150.0,
      "signal_week_end": "2026-03-05",
      "earliest_entry_date": null
    },
    {
      "symbol": "MWG",
      "asset_class": "stock",
      "action": "REDUCE",
      "buy_zone_low": 80.0,
      "buy_zone_high": 80.0,
      "stop_loss": 70.0,
      "take_profit": 90.0,
      "position_target_pct": 0.0,
      "rationale_bullets": [
        "Regime: BULL",
        "Trend WEAKENING: price 86 < MA10w 89",
        "Still above MA30w 82",
        "Consider reducing position"
      ],
      "entry_type": "pullback",
      "breakout_level": 0.0,
      "entry_price": 80.0,
      "signal_week_end": "2026-03-05",
      "earliest_entry_date": null
    }
  ],
  "notes": [
    "Regime-Adaptive Strategy | Current regime: BULL",
    "MA10w/MA30w trend + RSI(14)\u226550 momentum",
    "ATR(14)-based stops: 1.8x stop, 4.0x target",
    "Position sizing: 1.50x base allocation (config-driven)"
  ],
  "ai_analysis": {
    "generated": true,
    "market_context": "The portfolio has a total value of 9,999,966 VND, with a cash reserve of 99.98% and a single position, resulting in a net unrealized loss of 0.34%.",
    "analysis_date": "2026-03-05",
    "data_sources": "Weekly technical analysis using Groq AI",
    "scores": {
      "STB": {
        "symbol": "STB",
        "score": 8,
        "rationale": "Trend is up with price above both moving averages and RSI above 50.",
        "risk_note": "Stop loss is relatively close to the entry price."
      },
      "VIC": {
        "symbol": "VIC",
        "score": 9,
        "rationale": "Trend is strong with price above both moving averages and RSI above 50.",
        "risk_note": "Stop loss is relatively close to the entry price."
      },
      "MWG": {
        "symbol": "MWG",
        "score": 4,
        "rationale": "Trend is weakening with price below the short-term moving average.",
        "risk_note": "Reducing position indicates some risk of further price drop."
      }
    }
  },
  "news_analysis": {
    "symbol_scores": [
      {
        "symbol": "STB",
        "buy_potential_score": 20,
        "risk_score": 80,
        "confidence": 0.7,
        "horizon": "1-4w",
        "key_bull_points": [
          "Sacombank's new CEO, Nguy\u1ec5n \u0110\u1ee9c Th\u1ee5y, may bring positive changes to the bank (ID: 9d7bb7c27bd9ad51)"
        ],
        "key_risks": [
          "Xung \u0111\u1ed9t Trung \u0110\u00f4ng leo thang khi\u1ebfn nhi\u1ec1u doanh nghi\u1ec7p xu\u1ea5t kh\u1ea9u lo \u0111\u1ee9t g\u00e3y chu\u1ed7i cung \u1ee9ng, c\u01b0\u1edbc v\u1eadn t\u1ea3i t\u0103ng v\u1ecdt v\u00e0 r\u1ee7i ro h\u1ecfng n\u00f4ng s\u1ea3n t\u01b0\u01a1i (ID: 2eb65bcb5f9acd5a)",
          "\u00c1p l\u1ef1c b\u00e1n th\u00e1o tr\u00ean di\u1ec7n r\u1ed9ng khi\u1ebfn VN-Index m\u1ea5t h\u01a1n 34 \u0111i\u1ec3m (ID: b54b67fb5c3353dc)"
        ],
        "evidence": [
          {
            "id": "9d7bb7c27bd9ad51",
            "supports": "bull"
          },
          {
            "id": "2eb65bcb5f9acd5a",
            "supports": "risk"
          },
          {
            "id": "b54b67fb5c3353dc",
            "supports": "risk"
          }
        ]
      },
      {
        "symbol": "VIC",
        "buy_potential_score": 50,
        "risk_score": 50,
        "confidence": 0.0,
        "horizon": "1-4w",
        "key_bull_points": [],
        "key_risks": [],
        "evidence": []
      },
      {
        "symbol": "MWG",
        "buy_potential_score": 20,
        "risk_score": 60,
        "confidence": 0.8,
        "horizon": "1-4w",
        "key_bull_points": [
          "VN-Index gi\u1ea3m m\u1ea1nh nh\u1ea5t t\u1eeb \u0111\u1ea7u n\u0103m c\u00f3 th\u1ec3 \u1ea3nh h\u01b0\u1edfng \u0111\u1ebfn MWG nh\u01b0ng kh\u00f4ng r\u00f5 r\u00e0ng (b54b67fb5c3353dc)"
        ],
        "key_risks": [
          "Xung \u0111\u1ed9t Trung \u0110\u00f4ng c\u00f3 th\u1ec3 \u1ea3nh h\u01b0\u1edfng \u0111\u1ebfn chu\u1ed7i cung \u1ee9ng c\u1ee7a MWG (2eb65bcb5f9acd5a)",
          "\u0110\u1ecbnh gi\u00e1 c\u1ed5 phi\u1ebfu \u0111\u1ea7u kh\u00ed kh\u00f4ng c\u00f2n r\u1ebb, c\u00f3 th\u1ec3 \u1ea3nh h\u01b0\u1edfng \u0111\u1ebfn MWG (cdd34df7bc5f9f8d)"
        ],
        "evidence": [
          {
            "id": "b54b67fb5c3353dc",
            "supports": "neutral"
          },
          {
            "id": "2eb65bcb5f9acd5a",
            "supports": "risk"
          },
          {
            "id": "cdd34df7bc5f9f8d",
            "supports": "risk"
          }
        ]
      }
    ],
    "status": "SUCCESS",
    "analyzed_symbols": 3,
    "total_news": 10
  },
  "market_regime": "bull"
}